{
  "project_info": {
    "project_id": "yoshinani-c5ca",
    "project_number": "888587544463",
    "name": "YOSHINANI"
  },
  "client": [
    {
      "client_info": {
        "mobilesdk_app_id": "1:888587544463:android:8278001c91d1eac1",
        "client_id": "android:app.android.ttp.mikazuki.yoshinani",
        "client_type": 1,
        "android_client_info": {
          "package_name": "app.android.ttp.mikazuki.yoshinani"
        }
      },
      "oauth_client": [],
      "api_key": [],
      "services": {
        "analytics_service": {
          "status": 2,
          "analytics_property": {
            "tracking_id": "UA-64303218-3"
          }
        },
        "cloud_messaging_service": {
          "status": 1,
          "apns_config": []
        },
        "appinvite_service": {
          "status": 1,
          "other_platform_oauth_client": []
        },
        "google_signin_service": {
          "status": 1
        },
        "ads_service": {
          "status": 1
        }
      }
    },
    {
      "client_info": {
        "mobilesdk_app_id": "1:888587544463:android:4fb750af4fde204c",
        "client_id": "android:app.android.ttp.mikazuki.yoshinani.develop",
        "client_type": 1,
        "android_client_info": {
          "package_name": "app.android.ttp.mikazuki.yoshinani.develop"
        }
      },
      "oauth_client": [],
      "api_key": [],
      "services": {
        "analytics_service": {
          "status": 2,
          "analytics_property": {
            "tracking_id": "UA-64303218-3"
          }
        },
        "cloud_messaging_service": {
          "status": 1,
          "apns_config": []
        },
        "appinvite_service": {
          "status": 1,
          "other_platform_oauth_client": []
        },
        "google_signin_service": {
          "status": 1
        },
        "ads_service": {
          "status": 1
        }
      }
    }
  ],
  "client_info": [],
  "ARTIFACT_VERSION": "1"
}